easy_text_to_image/__init__.py
easy_text_to_image/color.py
easy_text_to_image/text_to_image.py
easy_text_to_image/test/__init__.py
easy_text_to_image/test/test_color.py
easy_text_to_image/test/test_text_to_image.py
Easy_Text_To_Image-0.3.0.dist-info/LICENSE
Easy_Text_To_Image-0.3.0.dist-info/METADATA
Easy_Text_To_Image-0.3.0.dist-info/WHEEL
Easy_Text_To_Image-0.3.0.dist-info/top_level.txt
Easy_Text_To_Image-0.3.0.dist-info/RECORD
